placeholder/__init__.py
PyPiPythonCodeThemeTest-1.0.0.dist-info/METADATA
PyPiPythonCodeThemeTest-1.0.0.dist-info/WHEEL
PyPiPythonCodeThemeTest-1.0.0.dist-info/top_level.txt
PyPiPythonCodeThemeTest-1.0.0.dist-info/RECORD
