Metadata-Version: 2.1
Name: PyPiPythonCodeThemeTest
Version: 1.0.0
Summary: This is a test for PyPi python formatting in markdown based READMEs.
Home-page: https://pypi.python.org/pypi/PyPiPythonCodeThemeTest
Author: Steven Shrewsbury
License: MIT
Platform: UNKNOWN
Requires-Python: >=3.6
